AUTHORS
INSTALL
LICENSE
MANIFEST.in
README
bootstrap.py
buildout.cfg
docs.cfg
setup.py
solvers.cfg
examples/AmericanSteelProblem.py
examples/BeerDistributionProblem.py
examples/CG.py
examples/CGcolumnwise.py
examples/ComputerPlantProblem.py
examples/SpongeRollProblem1.py
examples/SpongeRollProblem2.py
examples/SpongeRollProblem3.py
examples/SpongeRollProblem4.py
examples/SpongeRollProblem5.py
examples/SpongeRollProblem6.py
examples/Sudoku1.py
examples/Sudoku2.py
examples/WhiskasModel1.py
examples/WhiskasModel2.py
examples/furniture.py
examples/test1.py
examples/test2.py
examples/test3.py
examples/test4.py
examples/test5.py
examples/test6.py
examples/test7.py
examples/wedding.py
src/pulp/__init__.py
src/pulp/constants.py
src/pulp/odict.py
src/pulp/pulp.cfg.buildout
src/pulp/pulp.cfg.linux
src/pulp/pulp.cfg.win
src/pulp/pulp.py
src/pulp/solvers.py
src/pulp/sparse.py
src/pulp/solverdir/CoinMP.dll
src/pulp/solverdir/__init__.py
src/pulp/solverdir/libCbc.so
src/pulp/solverdir/libCbc.so.0
src/pulp/solverdir/libCbc.so.0.0.0
src/pulp/solverdir/libCbcSolver.so
src/pulp/solverdir/libCbcSolver.so.0
src/pulp/solverdir/libCbcSolver.so.0.0.0
src/pulp/solverdir/libCgl.so
src/pulp/solverdir/libCgl.so.0
src/pulp/solverdir/libCgl.so.0.0.0
src/pulp/solverdir/libClp.so
src/pulp/solverdir/libClp.so.0
src/pulp/solverdir/libClp.so.0.0.0
src/pulp/solverdir/libCoinMP.so
src/pulp/solverdir/libCoinMP.so.0
src/pulp/solverdir/libCoinMP.so.0.0.0
src/pulp/solverdir/libCoinUtils.so
src/pulp/solverdir/libCoinUtils.so.0
src/pulp/solverdir/libCoinUtils.so.0.0.0
src/pulp/solverdir/libOsi.so
src/pulp/solverdir/libOsi.so.0
src/pulp/solverdir/libOsi.so.0.0.0
src/pulp/solverdir/libOsiCbc.so
src/pulp/solverdir/libOsiCbc.so.0
src/pulp/solverdir/libOsiCbc.so.0.0.0
src/pulp/solverdir/libOsiClp.so
src/pulp/solverdir/libOsiClp.so.0
src/pulp/solverdir/libOsiClp.so.0.0.0
src/pulp_or.egg-info/PKG-INFO
src/pulp_or.egg-info/SOURCES.txt
src/pulp_or.egg-info/dependency_links.txt
src/pulp_or.egg-info/entry_points.txt
src/pulp_or.egg-info/top_level.txt