Metadata-Version: 1.0
Name: pulp-or
Version: 1.4.6
Summary: 
